{
  "ts": 1756919989.413353,
  "league": "Standard",
  "realm": "poe2",
  "pair_rates_full": {
    "('Orb of Alchemy', 'Orb of Alchemy')": 1.0,
    "('Orb of Annulment', 'Orb of Annulment')": 1.0,
    "(\"Artificer's Orb\", \"Artificer's Orb\")": 1.0,
    "('Orb of Augmentation', 'Orb of Augmentation')": 1.0,
    "('Orb of Chance', 'Orb of Chance')": 1.0,
    "('Chaos Orb', 'Chaos Orb')": 1.0,
    "('Divine Orb', 'Divine Orb')": 1.0,
    "(\"Arcanist's Etcher\", \"Arcanist's Etcher\")": 1.0,
    "('Exalted Orb', 'Exalted Orb')": 1.0,
    "('Fracturing Orb', 'Fracturing Orb')": 1.0,
    "('Mirror of Kalandra', 'Mirror of Kalandra')": 1.0,
    "('Regal Orb', 'Regal Orb')": 1.0,
    "('Orb of Transmutation', 'Orb of Transmutation')": 1.0,
    "('Vaal Orb', 'Vaal Orb')": 1.0,
    "('Orb of Alchemy', 'Orb of Annulment')": 1.0866666666666667,
    "('Orb of Alchemy', \"Artificer's Orb\")": 5.666666666666667,
    "('Orb of Alchemy', 'Orb of Augmentation')": 150.25,
    "('Orb of Alchemy', 'Orb of Chance')": 1.2142857142857142,
    "('Orb of Alchemy', 'Chaos Orb')": 1.1813543599257885,
    "('Orb of Alchemy', 'Divine Orb')": 0.7030375324725485,
    "('Orb of Alchemy', \"Arcanist's Etcher\")": 6.666666666666667,
    "('Orb of Alchemy', 'Exalted Orb')": 0.7265127807547095,
    "('Orb of Alchemy', 'Mirror of Kalandra')": 1.4375,
    "('Orb of Alchemy', 'Regal Orb')": 6.4,
    "('Orb of Alchemy', 'Orb of Transmutation')": 215.0,
    "('Orb of Alchemy', 'Vaal Orb')": 2.79,
    "('Orb of Annulment', 'Orb of Alchemy')": 52.45454545454545,
    "('Orb of Annulment', \"Artificer's Orb\")": 20.0,
    "('Orb of Annulment', 'Orb of Chance')": 2.6666666666666665,
    "('Orb of Annulment', 'Chaos Orb')": 6.428571428571429,
    "('Orb of Annulment', 'Divine Orb')": 0.6642152985902986,
    "('Orb of Annulment', 'Exalted Orb')": 3.78125,
    "('Orb of Annulment', 'Mirror of Kalandra')": 1.0,
    "('Orb of Annulment', 'Regal Orb')": 6.0,
    "('Orb of Annulment', 'Vaal Orb')": 26.0,
    "(\"Artificer's Orb\", 'Orb of Alchemy')": 3.951219512195122,
    "(\"Artificer's Orb\", 'Orb of Annulment')": 1.44,
    "(\"Artificer's Orb\", 'Orb of Augmentation')": 152.75,
    "(\"Artificer's Orb\", 'Orb of Chance')": 0.5625,
    "(\"Artificer's Orb\", 'Chaos Orb')": 3.695495495495496,
    "(\"Artificer's Orb\", 'Divine Orb')": 0.8342966435546666,
    "(\"Artificer's Orb\", 'Exalted Orb')": 0.7303264365332264,
    "(\"Artificer's Orb\", 'Fracturing Orb')": 0.02,
    "(\"Artificer's Orb\", 'Mirror of Kalandra')": 6.7894736842105265,
    "(\"Artificer's Orb\", 'Regal Orb')": 4.0,
    "(\"Artificer's Orb\", 'Orb of Transmutation')": 60.0,
    "(\"Artificer's Orb\", 'Vaal Orb')": 2.1666666666666665,
    "('Orb of Augmentation', 'Orb of Alchemy')": 0.9492382271468144,
    "('Orb of Augmentation', 'Orb of Annulment')": 0.604,
    "('Orb of Augmentation', \"Artificer's Orb\")": 1.4326797385620915,
    "('Orb of Augmentation', 'Orb of Chance')": 2.0,
    "('Orb of Augmentation', 'Chaos Orb')": 1.6521367689263184,
    "('Orb of Augmentation', 'Divine Orb')": 0.6992366499889319,
    "('Orb of Augmentation', 'Exalted Orb')": 0.035573837737039336,
    "('Orb of Augmentation', 'Mirror of Kalandra')": 2.40625,
    "('Orb of Augmentation', 'Regal Orb')": 1.534848484848485,
    "('Orb of Augmentation', 'Orb of Transmutation')": 0.991111111111111,
    "('Orb of Augmentation', 'Vaal Orb')": 1.0952380952380951,
    "('Orb of Chance', 'Orb of Alchemy')": 25.6,
    "('Orb of Chance', 'Orb of Annulment')": 1.5999999999999999,
    "('Orb of Chance', \"Artificer's Orb\")": 5.0,
    "('Orb of Chance', 'Chaos Orb')": 2.6818181818181817,
    "('Orb of Chance', 'Divine Orb')": 0.058746934379437496,
    "('Orb of Chance', 'Exalted Orb')": 3.622,
    "('Orb of Chance', 'Mirror of Kalandra')": 1.0,
    "('Orb of Chance', 'Regal Orb')": 136.66666666666666,
    "('Orb of Chance', 'Vaal Orb')": 32.0,
    "('Chaos Orb', 'Orb of Alchemy')": 14.714285714285715,
    "('Chaos Orb', 'Orb of Annulment')": 1.1111111111111112,
    "('Chaos Orb', \"Artificer's Orb\")": 81.66666666666667,
    "('Chaos Orb', 'Orb of Augmentation')": 288.5,
    "('Chaos Orb', 'Orb of Chance')": 3.4444444444444446,
    "('Chaos Orb', 'Divine Orb')": 0.05384133865678594,
    "('Chaos Orb', \"Arcanist's Etcher\")": 60.0,
    "('Chaos Orb', 'Exalted Orb')": 1.0,
    "('Chaos Orb', 'Mirror of Kalandra')": 8.65,
    "('Chaos Orb', 'Regal Orb')": 8.0,
    "('Chaos Orb', 'Orb of Transmutation')": 287.5,
    "('Chaos Orb', 'Vaal Orb')": 32.333333333333336,
    "('Divine Orb', 'Orb of Alchemy')": 513.5333333333333,
    "('Divine Orb', 'Orb of Annulment')": 25.90909090909091,
    "('Divine Orb', \"Artificer's Orb\")": 505.0,
    "('Divine Orb', 'Orb of Chance')": 111.35714285714286,
    "('Divine Orb', 'Chaos Orb')": 42.8125,
    "('Divine Orb', \"Arcanist's Etcher\")": 766.6666666666666,
    "('Divine Orb', 'Exalted Orb')": 69.27368421052631,
    "('Divine Orb', 'Fracturing Orb')": 4.3125,
    "('Divine Orb', 'Mirror of Kalandra')": 3.4215080163011127,
    "('Divine Orb', 'Regal Orb')": 1042.0,
    "('Divine Orb', 'Orb of Transmutation')": 1.0,
    "('Divine Orb', 'Vaal Orb')": 835.9090909090909,
    "(\"Arcanist's Etcher\", 'Orb of Alchemy')": 13.180327868852459,
    "(\"Arcanist's Etcher\", 'Orb of Annulment')": 1.0,
    "(\"Arcanist's Etcher\", \"Artificer's Orb\")": 1.6666666666666667,
    "(\"Arcanist's Etcher\", 'Orb of Augmentation')": 12.5,
    "(\"Arcanist's Etcher\", 'Orb of Chance')": 2.125,
    "(\"Arcanist's Etcher\", 'Chaos Orb')": 1.8263888888888886,
    "(\"Arcanist's Etcher\", 'Divine Orb')": 0.8310419004232636,
    "(\"Arcanist's Etcher\", 'Exalted Orb')": 0.7212014885699097,
    "(\"Arcanist's Etcher\", 'Mirror of Kalandra')": 51.6875,
    "(\"Arcanist's Etcher\", 'Regal Orb')": 2.0714285714285716,
    "(\"Arcanist's Etcher\", 'Orb of Transmutation')": 37.666666666666664,
    "('Exalted Orb', 'Orb of Alchemy')": 3.7415714285714285,
    "('Exalted Orb', 'Orb of Annulment')": 0.4187727642508749,
    "('Exalted Orb', \"Artificer's Orb\")": 5.9316633597883595,
    "('Exalted Orb', 'Orb of Augmentation')": 288.46666666666664,
    "('Exalted Orb', 'Orb of Chance')": 0.5600044497513506,
    "('Exalted Orb', 'Chaos Orb')": 0.4962698034608836,
    "('Exalted Orb', 'Divine Orb')": 0.0029867892728923356,
    "('Exalted Orb', \"Arcanist's Etcher\")": 5.261666666666667,
    "('Exalted Orb', 'Fracturing Orb')": 0.3423333333333333,
    "('Exalted Orb', 'Mirror of Kalandra')": 4.408690476190476,
    "('Exalted Orb', 'Regal Orb')": 11.978584232668739,
    "('Exalted Orb', 'Orb of Transmutation')": 104.16666666666667,
    "('Exalted Orb', 'Vaal Orb')": 6.0209150326797385,
    "('Fracturing Orb', 'Orb of Alchemy')": 1.0,
    "('Fracturing Orb', 'Orb of Annulment')": 2.0,
    "('Fracturing Orb', 'Chaos Orb')": 8.6,
    "('Fracturing Orb', 'Divine Orb')": 2.074074074074074,
    "('Fracturing Orb', 'Exalted Orb')": 229.375,
    "('Mirror of Kalandra', 'Divine Orb')": 2151.1111111111113,
    "('Regal Orb', 'Orb of Alchemy')": 7.3,
    "('Regal Orb', 'Orb of Annulment')": 0.926530612244898,
    "('Regal Orb', \"Artificer's Orb\")": 2.642857142857143,
    "('Regal Orb', 'Orb of Augmentation')": 84.55555555555556,
    "('Regal Orb', 'Orb of Chance')": 1.0814814814814815,
    "('Regal Orb', 'Chaos Orb')": 1.471459089433773,
    "('Regal Orb', 'Divine Orb')": 0.5902325010809641,
    "('Regal Orb', \"Arcanist's Etcher\")": 3.75,
    "('Regal Orb', 'Exalted Orb')": 0.2170132660333643,
    "('Regal Orb', 'Mirror of Kalandra')": 1.2105263157894737,
    "('Regal Orb', 'Orb of Transmutation')": 32.666666666666664,
    "('Regal Orb', 'Vaal Orb')": 1.3040752351097178,
    "('Orb of Transmutation', 'Orb of Alchemy')": 0.9483253588516747,
    "('Orb of Transmutation', 'Orb of Annulment')": 1.0083333333333333,
    "('Orb of Transmutation', \"Artificer's Orb\")": 1.657142857142857,
    "('Orb of Transmutation', 'Orb of Augmentation')": 2.123456790123457,
    "('Orb of Transmutation', 'Orb of Chance')": 26.5,
    "('Orb of Transmutation', 'Chaos Orb')": 1.7996359824661712,
    "('Orb of Transmutation', 'Divine Orb')": 0.770592907896145,
    "('Orb of Transmutation', 'Exalted Orb')": 0.05039970597420883,
    "('Orb of Transmutation', 'Mirror of Kalandra')": 23.0,
    "('Orb of Transmutation', 'Regal Orb')": 2.3181818181818183,
    "('Orb of Transmutation', 'Vaal Orb')": 1.0833333333333333,
    "('Vaal Orb', 'Orb of Alchemy')": 1.875,
    "('Vaal Orb', 'Orb of Annulment')": 0.8518518518518517,
    "('Vaal Orb', \"Artificer's Orb\")": 2.125,
    "('Vaal Orb', 'Orb of Augmentation')": 25.5,
    "('Vaal Orb', 'Orb of Chance')": 1.2619047619047616,
    "('Vaal Orb', 'Chaos Orb')": 5.616300366300367,
    "('Vaal Orb', 'Divine Orb')": 0.605989862321196,
    "('Vaal Orb', 'Exalted Orb')": 0.6984784317261825,
    "('Vaal Orb', 'Fracturing Orb')": 0.02,
    "('Vaal Orb', 'Mirror of Kalandra')": 1.1904761904761905,
    "('Vaal Orb', 'Regal Orb')": 7.153846153846154,
    "('Vaal Orb', 'Orb of Transmutation')": 41.75
  },
  "pair_rates_short": {
    "('alch', 'alch')": 1.0,
    "('annul', 'annul')": 1.0,
    "('artificers', 'artificers')": 1.0,
    "('aug', 'aug')": 1.0,
    "('chance', 'chance')": 1.0,
    "('chaos', 'chaos')": 1.0,
    "('divine', 'divine')": 1.0,
    "('etcher', 'etcher')": 1.0,
    "('exalted', 'exalted')": 1.0,
    "('fracturing-orb', 'fracturing-orb')": 1.0,
    "('mirror', 'mirror')": 1.0,
    "('regal', 'regal')": 1.0,
    "('transmute', 'transmute')": 1.0,
    "('vaal', 'vaal')": 1.0,
    "('alch', 'annul')": 1.0866666666666667,
    "('alch', 'artificers')": 5.666666666666667,
    "('alch', 'aug')": 150.25,
    "('alch', 'chance')": 1.2142857142857142,
    "('alch', 'chaos')": 1.1813543599257885,
    "('alch', 'divine')": 0.7030375324725485,
    "('alch', 'etcher')": 6.666666666666667,
    "('alch', 'exalted')": 0.7265127807547095,
    "('alch', 'mirror')": 1.4375,
    "('alch', 'regal')": 6.4,
    "('alch', 'transmute')": 215.0,
    "('alch', 'vaal')": 2.79,
    "('annul', 'alch')": 52.45454545454545,
    "('annul', 'artificers')": 20.0,
    "('annul', 'chance')": 2.6666666666666665,
    "('annul', 'chaos')": 6.428571428571429,
    "('annul', 'divine')": 0.6642152985902986,
    "('annul', 'exalted')": 3.78125,
    "('annul', 'mirror')": 1.0,
    "('annul', 'regal')": 6.0,
    "('annul', 'vaal')": 26.0,
    "('artificers', 'alch')": 3.951219512195122,
    "('artificers', 'annul')": 1.44,
    "('artificers', 'aug')": 152.75,
    "('artificers', 'chance')": 0.5625,
    "('artificers', 'chaos')": 3.695495495495496,
    "('artificers', 'divine')": 0.8342966435546666,
    "('artificers', 'exalted')": 0.7303264365332264,
    "('artificers', 'fracturing-orb')": 0.02,
    "('artificers', 'mirror')": 6.7894736842105265,
    "('artificers', 'regal')": 4.0,
    "('artificers', 'transmute')": 60.0,
    "('artificers', 'vaal')": 2.1666666666666665,
    "('aug', 'alch')": 0.9492382271468144,
    "('aug', 'annul')": 0.604,
    "('aug', 'artificers')": 1.4326797385620915,
    "('aug', 'chance')": 2.0,
    "('aug', 'chaos')": 1.6521367689263184,
    "('aug', 'divine')": 0.6992366499889319,
    "('aug', 'exalted')": 0.035573837737039336,
    "('aug', 'mirror')": 2.40625,
    "('aug', 'regal')": 1.534848484848485,
    "('aug', 'transmute')": 0.991111111111111,
    "('aug', 'vaal')": 1.0952380952380951,
    "('chance', 'alch')": 25.6,
    "('chance', 'annul')": 1.5999999999999999,
    "('chance', 'artificers')": 5.0,
    "('chance', 'chaos')": 2.6818181818181817,
    "('chance', 'divine')": 0.058746934379437496,
    "('chance', 'exalted')": 3.622,
    "('chance', 'mirror')": 1.0,
    "('chance', 'regal')": 136.66666666666666,
    "('chance', 'vaal')": 32.0,
    "('chaos', 'alch')": 14.714285714285715,
    "('chaos', 'annul')": 1.1111111111111112,
    "('chaos', 'artificers')": 81.66666666666667,
    "('chaos', 'aug')": 288.5,
    "('chaos', 'chance')": 3.4444444444444446,
    "('chaos', 'divine')": 0.05384133865678594,
    "('chaos', 'etcher')": 60.0,
    "('chaos', 'exalted')": 1.0,
    "('chaos', 'mirror')": 8.65,
    "('chaos', 'regal')": 8.0,
    "('chaos', 'transmute')": 287.5,
    "('chaos', 'vaal')": 32.333333333333336,
    "('divine', 'alch')": 513.5333333333333,
    "('divine', 'annul')": 25.90909090909091,
    "('divine', 'artificers')": 505.0,
    "('divine', 'chance')": 111.35714285714286,
    "('divine', 'chaos')": 42.8125,
    "('divine', 'etcher')": 766.6666666666666,
    "('divine', 'exalted')": 69.27368421052631,
    "('divine', 'fracturing-orb')": 4.3125,
    "('divine', 'mirror')": 3.4215080163011127,
    "('divine', 'regal')": 1042.0,
    "('divine', 'transmute')": 1.0,
    "('divine', 'vaal')": 835.9090909090909,
    "('etcher', 'alch')": 13.180327868852459,
    "('etcher', 'annul')": 1.0,
    "('etcher', 'artificers')": 1.6666666666666667,
    "('etcher', 'aug')": 12.5,
    "('etcher', 'chance')": 2.125,
    "('etcher', 'chaos')": 1.8263888888888886,
    "('etcher', 'divine')": 0.8310419004232636,
    "('etcher', 'exalted')": 0.7212014885699097,
    "('etcher', 'mirror')": 51.6875,
    "('etcher', 'regal')": 2.0714285714285716,
    "('etcher', 'transmute')": 37.666666666666664,
    "('exalted', 'alch')": 3.7415714285714285,
    "('exalted', 'annul')": 0.4187727642508749,
    "('exalted', 'artificers')": 5.9316633597883595,
    "('exalted', 'aug')": 288.46666666666664,
    "('exalted', 'chance')": 0.5600044497513506,
    "('exalted', 'chaos')": 0.4962698034608836,
    "('exalted', 'divine')": 0.0029867892728923356,
    "('exalted', 'etcher')": 5.261666666666667,
    "('exalted', 'fracturing-orb')": 0.3423333333333333,
    "('exalted', 'mirror')": 4.408690476190476,
    "('exalted', 'regal')": 11.978584232668739,
    "('exalted', 'transmute')": 104.16666666666667,
    "('exalted', 'vaal')": 6.0209150326797385,
    "('fracturing-orb', 'alch')": 1.0,
    "('fracturing-orb', 'annul')": 2.0,
    "('fracturing-orb', 'chaos')": 8.6,
    "('fracturing-orb', 'divine')": 2.074074074074074,
    "('fracturing-orb', 'exalted')": 229.375,
    "('mirror', 'divine')": 2151.1111111111113,
    "('regal', 'alch')": 7.3,
    "('regal', 'annul')": 0.926530612244898,
    "('regal', 'artificers')": 2.642857142857143,
    "('regal', 'aug')": 84.55555555555556,
    "('regal', 'chance')": 1.0814814814814815,
    "('regal', 'chaos')": 1.471459089433773,
    "('regal', 'divine')": 0.5902325010809641,
    "('regal', 'etcher')": 3.75,
    "('regal', 'exalted')": 0.2170132660333643,
    "('regal', 'mirror')": 1.2105263157894737,
    "('regal', 'transmute')": 32.666666666666664,
    "('regal', 'vaal')": 1.3040752351097178,
    "('transmute', 'alch')": 0.9483253588516747,
    "('transmute', 'annul')": 1.0083333333333333,
    "('transmute', 'artificers')": 1.657142857142857,
    "('transmute', 'aug')": 2.123456790123457,
    "('transmute', 'chance')": 26.5,
    "('transmute', 'chaos')": 1.7996359824661712,
    "('transmute', 'divine')": 0.770592907896145,
    "('transmute', 'exalted')": 0.05039970597420883,
    "('transmute', 'mirror')": 23.0,
    "('transmute', 'regal')": 2.3181818181818183,
    "('transmute', 'vaal')": 1.0833333333333333,
    "('vaal', 'alch')": 1.875,
    "('vaal', 'annul')": 0.8518518518518517,
    "('vaal', 'artificers')": 2.125,
    "('vaal', 'aug')": 25.5,
    "('vaal', 'chance')": 1.2619047619047616,
    "('vaal', 'chaos')": 5.616300366300367,
    "('vaal', 'divine')": 0.605989862321196,
    "('vaal', 'exalted')": 0.6984784317261825,
    "('vaal', 'fracturing-orb')": 0.02,
    "('vaal', 'mirror')": 1.1904761904761905,
    "('vaal', 'regal')": 7.153846153846154,
    "('vaal', 'transmute')": 41.75
  },
  "short_map": {
    "alch": "Orb of Alchemy",
    "annul": "Orb of Annulment",
    "artificers": "Artificer's Orb",
    "aug": "Orb of Augmentation",
    "chance": "Orb of Chance",
    "chaos": "Chaos Orb",
    "divine": "Divine Orb",
    "etcher": "Arcanist's Etcher",
    "exalted": "Exalted Orb",
    "fracturing-orb": "Fracturing Orb",
    "mirror": "Mirror of Kalandra",
    "regal": "Regal Orb",
    "transmute": "Orb of Transmutation",
    "vaal": "Vaal Orb"
  },
  "full_map": {
    "Orb of Alchemy": "alch",
    "Orb of Annulment": "annul",
    "Artificer's Orb": "artificers",
    "Orb of Augmentation": "aug",
    "Orb of Chance": "chance",
    "Chaos Orb": "chaos",
    "Divine Orb": "divine",
    "Arcanist's Etcher": "etcher",
    "Exalted Orb": "exalted",
    "Fracturing Orb": "fracturing-orb",
    "Mirror of Kalandra": "mirror",
    "Regal Orb": "regal",
    "Orb of Transmutation": "transmute",
    "Vaal Orb": "vaal"
  }
}